<?xml version="1.0" encoding="UTF-8" standalone="yes"?>
<ns3:FileMetadati xmlns:ns2="http://www.w3.org/2000/09/xmldsig#" xmlns:ns3="http://ivaservizi.agenziaentrate.gov.it/docs/xsd/fattura/messaggi/v1.0" versione="1.0">
    <IdentificativoSdI>14608194780</IdentificativoSdI>
    <NomeFile>IT07614280969_016WL.xml.p7m</NomeFile>
    <Hash>8ddded08d2267ca563dd37f7cdc0da46ddcd1b52e94d86a36a3228ed105ef3bf</Hash>
    <CodiceDestinatario>SUBM70N</CodiceDestinatario>
    <Formato>FPR12</Formato>
    <TentativiInvio>1</TentativiInvio>
    <MessageId>35268052227</MessageId>
</ns3:FileMetadati>
